audioinfo/__init__.py
audioinfo/main.py
audioinfo-0.2.1.dist-info/entry_points.txt
audioinfo-0.2.1.dist-info/LICENSE
audioinfo-0.2.1.dist-info/WHEEL
audioinfo-0.2.1.dist-info/METADATA
audioinfo-0.2.1.dist-info/RECORD
