Metadata-Version: 2.1
Name: audioinfo
Version: 0.2.1
Summary: Count audio files in a directory.
Author-email: HAO Xiang <haoxiangsnr@gmail.com>
Requires-Python: >=3.8
Classifier: Programming Language :: Python :: 3.8
Classifier: Development Status :: 2 - Pre-Alpha
Classifier: License :: OSI Approved :: MIT License
Classifier: Environment :: GPU :: NVIDIA CUDA
Classifier: Operating System :: OS Independent
Requires-Dist: soundfile
Requires-Dist: numpy
Requires-Dist: plotille
Requires-Dist: rich
Requires-Dist: flit ; extra == "build"
Requires-Dist: python-semantic-release ; extra == "build"
Requires-Dist: pytest ; extra == "test"
Requires-Dist: pytest-cov ; extra == "test"
Project-URL: Documentation, https://github.com/haoxiangsnr/audioinfo
Project-URL: Source, https://github.com/haoxiangsnr/audioinfo
Provides-Extra: build
Provides-Extra: test
